{"format":2,"version":"7.1.0","globals":"d7ea3114d8281321ce1d30850d2d5eac","files":{"d_7fd85dc58871e5c7_front_matter_py":{"hash":"a594f66777a4808bed7fa3b52f2ad4b1","index":{"nums":[0,1,103,0,10,0,0,0],"html_filename":"d_7fd85dc58871e5c7_front_matter_py.html","relative_filename":"src/midgy/front_matter.py"}},"d_7fd85dc58871e5c7_lexers_py":{"hash":"66fc184a8631fd388787a8c0a34d9b61","index":{"nums":[0,1,74,0,4,0,0,0],"html_filename":"d_7fd85dc58871e5c7_lexers_py.html","relative_filename":"src/midgy/lexers.py"}},"d_7fd85dc58871e5c7_loader_py":{"hash":"bf4fa55531cc976659ec878e5459a410","index":{"nums":[0,1,23,0,23,0,0,0],"html_filename":"d_7fd85dc58871e5c7_loader_py.html","relative_filename":"src/midgy/loader.py"}},"d_7fd85dc58871e5c7_python_py":{"hash":"a2a6e5c0cc0782063c5a40ed759939e1","index":{"nums":[0,1,147,0,0,0,0,0],"html_filename":"d_7fd85dc58871e5c7_python_py.html","relative_filename":"src/midgy/python.py"}},"d_7fd85dc58871e5c7_render_py":{"hash":"b1ca7ccd4ecaaa451014856b7456498f","index":{"nums":[0,1,148,0,5,0,0,0],"html_filename":"d_7fd85dc58871e5c7_render_py.html","relative_filename":"src/midgy/render.py"}}}}